hintcast/__init__.py
hintcast/hintcast.py
hintcast-0.1.0.dist-info/LICENSE
hintcast-0.1.0.dist-info/METADATA
hintcast-0.1.0.dist-info/WHEEL
hintcast-0.1.0.dist-info/top_level.txt
hintcast-0.1.0.dist-info/RECORD
