Metadata-Version: 2.1
Name: hintcast
Version: 0.1.0
Summary: Decorators that allow for automatic type-casting of arguments for a function or strict enforcement of type hints.
Home-page: https://github.com/davocarli/hintcast
Author: David Carli-Arnold
Author-email: davocarli@gmail.com
License: MIT
Keywords: casting,typecast,type-cast,type-hints,hints,types,python,decorator
Platform: UNKNOWN
Classifier: Development Status :: 4 - Beta
Classifier: Intended Audience :: Developers
Classifier: License :: OSI Approved :: MIT License
Classifier: Programming Language :: Python :: 3.5
Classifier: Programming Language :: Python :: 3.6
Classifier: Programming Language :: Python :: 3.7
Classifier: Programming Language :: Python :: 3.8
Classifier: Programming Language :: Python :: 3.9
Classifier: Programming Language :: Python :: 3.10
Classifier: Topic :: Utilities
Classifier: Typing :: Typed
